pyramid_twitcher-0.11.1.dist-info/licenses/AUTHORS.rst
pyramid_twitcher-0.11.1.dist-info/licenses/LICENSE.txt
tests/__init__.py
tests/common.py
tests/test_adapter.py
tests/test_frontpage.py
tests/test_namesgenerator.py
tests/test_owsregistry.py
tests/test_owsrequest_wms.py
tests/test_owsrequest_wps.py
tests/test_store.py
tests/test_utils.py
tests/functional/__init__.py
tests/functional/base.py
tests/functional/test_adapter.py
tests/functional/test_api.py
tests/functional/test_oauth2_app.py
tests/functional/test_owsproxy_app.py
twitcher/__init__.py
twitcher/__version__.py
twitcher/api.py
twitcher/basicauth.py
twitcher/client.py
twitcher/exceptions.py
twitcher/frontpage.py
twitcher/interface.py
twitcher/namesgenerator.py
twitcher/oauth2.py
twitcher/owsexceptions.py
twitcher/owsproxy.py
twitcher/owsregistry.py
twitcher/owsrequest.py
twitcher/owssecurity.py
twitcher/store.py
twitcher/typedefs.py
twitcher/utils.py
twitcher/adapter/__init__.py
twitcher/adapter/base.py
twitcher/adapter/default.py
twitcher/alembic/env.py
twitcher/alembic/script.py.mako
twitcher/alembic/versions/20190510_d39766e64a84.py
twitcher/alembic/versions/20190605_1ab5b6358dd5.py
twitcher/alembic/versions/20190628_0a075bcbeb8f.py
twitcher/alembic/versions/20190723_b8aa09688558.py
twitcher/alembic/versions/20190724_d9cff565b8db.py
twitcher/alembic/versions/README.txt
twitcher/models/__init__.py
twitcher/models/meta.py
twitcher/models/oauth.py
twitcher/models/service.py
twitcher/scripts/__init__.py
twitcher/scripts/initialize_db.py
twitcher/scripts/twitcherctl.py
pyramid_twitcher-0.11.1.dist-info/METADATA
pyramid_twitcher-0.11.1.dist-info/WHEEL
pyramid_twitcher-0.11.1.dist-info/entry_points.txt
pyramid_twitcher-0.11.1.dist-info/top_level.txt
pyramid_twitcher-0.11.1.dist-info/RECORD
