Metadata-Version: 2.4
Name: pyramid_twitcher
Version: 0.11.1
Summary: Security Proxy for OGC Services like WPS.
Home-page: https://github.com/bird-house/twitcher.git
Author: Carsten Ehbrecht
Author-email: ehbrecht@dkrz.de
License: Apache License 2.0
Keywords: web pyramid twitcher birdhouse wps security proxy ows ogc
Classifier: Development Status :: 5 - Production/Stable
Classifier: Framework :: Pyramid
Classifier: Intended Audience :: Developers
Classifier: License :: OSI Approved :: Apache Software License
Classifier: Natural Language :: English
Classifier: Programming Language :: Python
Classifier: Programming Language :: Python :: 3.8
Classifier: Programming Language :: Python :: 3.9
Classifier: Programming Language :: Python :: 3.10
Classifier: Programming Language :: Python :: 3.11
Classifier: Programming Language :: Python :: 3.12
Classifier: Programming Language :: Python :: 3.13
Classifier: Topic :: Internet :: WWW/HTTP
Classifier: Topic :: Internet :: WWW/HTTP :: WSGI :: Application
Requires-Python: >=3.8, <4
License-File: LICENSE.txt
License-File: AUTHORS.rst
Requires-Dist: pyramid<2,>=1.10
Requires-Dist: webob
Requires-Dist: argcomplete
Requires-Dist: pytz
Requires-Dist: lxml
Requires-Dist: pyopenssl
Requires-Dist: cornice
Requires-Dist: cornice_swagger
Requires-Dist: colander
Requires-Dist: pyramid_debugtoolbar
Requires-Dist: plaster_pastedeploy
Requires-Dist: gunicorn
Requires-Dist: waitress==3.0.0; python_version < "3.9"
Requires-Dist: waitress>=3.0.2; python_version >= "3.9"
Requires-Dist: pyramid_retry
Requires-Dist: pyramid_tm
Requires-Dist: alembic
Requires-Dist: sqlalchemy<2,>=1.3
Requires-Dist: transaction
Requires-Dist: zope.sqlalchemy!=1.4.*,>=1.3
Requires-Dist: pyramid_oauthlib>=0.4.1
Requires-Dist: oauthlib<3
Requires-Dist: requests>=2.32.4; python_version < "3.9"
Requires-Dist: requests>=2.32.5; python_version >= "3.9"
Requires-Dist: requests_oauthlib<1.2.0
Requires-Dist: PyJWT>=2
Requires-Dist: setuptools==75.3.2; python_version < "3.9"
Requires-Dist: setuptools>=78.1.1; python_version >= "3.9"
Requires-Dist: urllib3>=2.2.2; python_version < "3.9"
Requires-Dist: urllib3>=2.6.3; python_version >= "3.9"
Requires-Dist: zipp>=3.19.1
Provides-Extra: dev
Requires-Dist: pytest>=5.0.0; extra == "dev"
Requires-Dist: pytest-cov; extra == "dev"
Requires-Dist: WebTest; extra == "dev"
Requires-Dist: flake8; extra == "dev"
Requires-Dist: sphinx; extra == "dev"
Requires-Dist: nbsphinx; extra == "dev"
Requires-Dist: bump2version; extra == "dev"
Requires-Dist: twine; extra == "dev"
Requires-Dist: mock; extra == "dev"
Requires-Dist: tornado>=6.4.2; extra == "dev"
Provides-Extra: postgres
Requires-Dist: psycopg2; extra == "postgres"
Dynamic: author
Dynamic: author-email
Dynamic: classifier
Dynamic: description
Dynamic: description-content-type
Dynamic: home-page
Dynamic: keywords
Dynamic: license
Dynamic: license-file
Dynamic: provides-extra
Dynamic: requires-dist
Dynamic: requires-python
Dynamic: summary
